niwrap_niftyreg/niftyreg/__init__.py
niwrap_niftyreg/niftyreg/reg_aladin.py
niwrap_niftyreg/niftyreg/reg_average.py
niwrap_niftyreg/niftyreg/reg_f3d.py
niwrap_niftyreg/niftyreg/reg_jacobian.py
niwrap_niftyreg/niftyreg/reg_resample.py
niwrap_niftyreg/niftyreg/reg_tools.py
niwrap_niftyreg/niftyreg/reg_transform.py
niwrap_niftyreg-0.8.3.dist-info/WHEEL
niwrap_niftyreg-0.8.3.dist-info/METADATA
niwrap_niftyreg-0.8.3.dist-info/RECORD
